<annotation>
	<folder>Images</folder>
	<filename>0031.png</filename>
	<path>D:\20190529data_label\D1_100\Images\0031.png</path>
	<source>
		<database>Unknown</database>
	</source>
	<size>
		<width>2400</width>
		<height>1380</height>
		<depth>3</depth>
	</size>
	<segmented>0</segmented>
	<object>
		<name>btn-active</name>
		<pose>Unspecified</pose>
		<truncated>1</truncated>
		<difficult>0</difficult>
		<bndbox>
			<xmin>45</xmin>
			<ymin>1</ymin>
			<xmax>221</xmax>
			<ymax>117</ymax>
		</bndbox>
	</object>
	<object>
		<name>btn-active</name>
		<pose>Unspecified</pose>
		<truncated>1</truncated>
		<difficult>0</difficult>
		<bndbox>
			<xmin>230</xmin>
			<ymin>1</ymin>
			<xmax>406</xmax>
			<ymax>117</ymax>
		</bndbox>
	</object>
	<object>
		<name>btn-active</name>
		<pose>Unspecified</pose>
		<truncated>0</truncated>
		<difficult>0</difficult>
		<bndbox>
			<xmin>57</xmin>
			<ymin>324</ymin>
			<xmax>205</xmax>
			<ymax>421</ymax>
		</bndbox>
	</object>
	<object>
		<name>btn-active</name>
		<pose>Unspecified</pose>
		<truncated>0</truncated>
		<difficult>0</difficult>
		<bndbox>
			<xmin>1255</xmin>
			<ymin>322</ymin>
			<xmax>1419</xmax>
			<ymax>414</ymax>
		</bndbox>
	</object>
	<object>
		<name>btn-active</name>
		<pose>Unspecified</pose>
		<truncated>0</truncated>
		<difficult>0</difficult>
		<bndbox>
			<xmin>55</xmin>
			<ymin>737</ymin>
			<xmax>219</xmax>
			<ymax>829</ymax>
		</bndbox>
	</object>
	<object>
		<name>btn-active</name>
		<pose>Unspecified</pose>
		<truncated>0</truncated>
		<difficult>0</difficult>
		<bndbox>
			<xmin>651</xmin>
			<ymin>735</ymin>
			<xmax>815</xmax>
			<ymax>827</ymax>
		</bndbox>
	</object>
	<object>
		<name>btn-active</name>
		<pose>Unspecified</pose>
		<truncated>0</truncated>
		<difficult>0</difficult>
		<bndbox>
			<xmin>1244</xmin>
			<ymin>733</ymin>
			<xmax>1420</xmax>
			<ymax>828</ymax>
		</bndbox>
	</object>
	<object>
		<name>btn-active</name>
		<pose>Unspecified</pose>
		<truncated>0</truncated>
		<difficult>0</difficult>
		<bndbox>
			<xmin>1828</xmin>
			<ymin>739</ymin>
			<xmax>2004</xmax>
			<ymax>834</ymax>
		</bndbox>
	</object>
	<object>
		<name>small-title</name>
		<pose>Unspecified</pose>
		<truncated>0</truncated>
		<difficult>0</difficult>
		<bndbox>
			<xmin>64</xmin>
			<ymin>179</ymin>
			<xmax>200</xmax>
			<ymax>265</ymax>
		</bndbox>
	</object>
	<object>
		<name>small-title</name>
		<pose>Unspecified</pose>
		<truncated>0</truncated>
		<difficult>0</difficult>
		<bndbox>
			<xmin>1263</xmin>
			<ymin>182</ymin>
			<xmax>1425</xmax>
			<ymax>265</ymax>
		</bndbox>
	</object>
	<object>
		<name>small-title</name>
		<pose>Unspecified</pose>
		<truncated>0</truncated>
		<difficult>0</difficult>
		<bndbox>
			<xmin>64</xmin>
			<ymin>546</ymin>
			<xmax>227</xmax>
			<ymax>628</ymax>
		</bndbox>
	</object>
	<object>
		<name>small-title</name>
		<pose>Unspecified</pose>
		<truncated>0</truncated>
		<difficult>0</difficult>
		<bndbox>
			<xmin>652</xmin>
			<ymin>548</ymin>
			<xmax>856</xmax>
			<ymax>624</ymax>
		</bndbox>
	</object>
	<object>
		<name>small-title</name>
		<pose>Unspecified</pose>
		<truncated>0</truncated>
		<difficult>0</difficult>
		<bndbox>
			<xmin>1241</xmin>
			<ymin>546</ymin>
			<xmax>1445</xmax>
			<ymax>622</ymax>
		</bndbox>
	</object>
	<object>
		<name>small-title</name>
		<pose>Unspecified</pose>
		<truncated>0</truncated>
		<difficult>0</difficult>
		<bndbox>
			<xmin>1825</xmin>
			<ymin>559</ymin>
			<xmax>2029</xmax>
			<ymax>635</ymax>
		</bndbox>
	</object>
	<object>
		<name>text</name>
		<pose>Unspecified</pose>
		<truncated>0</truncated>
		<difficult>0</difficult>
		<bndbox>
			<xmin>66</xmin>
			<ymin>272</ymin>
			<xmax>808</xmax>
			<ymax>326</ymax>
		</bndbox>
	</object>
	<object>
		<name>text</name>
		<pose>Unspecified</pose>
		<truncated>0</truncated>
		<difficult>0</difficult>
		<bndbox>
			<xmin>1244</xmin>
			<ymin>272</ymin>
			<xmax>1986</xmax>
			<ymax>326</ymax>
		</bndbox>
	</object>
	<object>
		<name>text</name>
		<pose>Unspecified</pose>
		<truncated>0</truncated>
		<difficult>0</difficult>
		<bndbox>
			<xmin>60</xmin>
			<ymin>627</ymin>
			<xmax>530</xmax>
			<ymax>729</ymax>
		</bndbox>
	</object>
	<object>
		<name>text</name>
		<pose>Unspecified</pose>
		<truncated>0</truncated>
		<difficult>0</difficult>
		<bndbox>
			<xmin>639</xmin>
			<ymin>627</ymin>
			<xmax>1109</xmax>
			<ymax>729</ymax>
		</bndbox>
	</object>
	<object>
		<name>text</name>
		<pose>Unspecified</pose>
		<truncated>0</truncated>
		<difficult>0</difficult>
		<bndbox>
			<xmin>1239</xmin>
			<ymin>625</ymin>
			<xmax>1741</xmax>
			<ymax>735</ymax>
		</bndbox>
	</object>
	<object>
		<name>text</name>
		<pose>Unspecified</pose>
		<truncated>0</truncated>
		<difficult>0</difficult>
		<bndbox>
			<xmin>1824</xmin>
			<ymin>642</ymin>
			<xmax>2363</xmax>
			<ymax>731</ymax>
		</bndbox>
	</object>
	<object>
		<name>double</name>
		<pose>Unspecified</pose>
		<truncated>0</truncated>
		<difficult>0</difficult>
		<bndbox>
			<xmin>19</xmin>
			<ymin>124</ymin>
			<xmax>1193</xmax>
			<ymax>479</ymax>
		</bndbox>
	</object>
	<object>
		<name>double</name>
		<pose>Unspecified</pose>
		<truncated>0</truncated>
		<difficult>0</difficult>
		<bndbox>
			<xmin>1197</xmin>
			<ymin>122</ymin>
			<xmax>2388</xmax>
			<ymax>482</ymax>
		</bndbox>
	</object>
	<object>
		<name>quadruple</name>
		<pose>Unspecified</pose>
		<truncated>0</truncated>
		<difficult>0</difficult>
		<bndbox>
			<xmin>6</xmin>
			<ymin>471</ymin>
			<xmax>610</xmax>
			<ymax>882</ymax>
		</bndbox>
	</object>
	<object>
		<name>quadruple</name>
		<pose>Unspecified</pose>
		<truncated>0</truncated>
		<difficult>0</difficult>
		<bndbox>
			<xmin>603</xmin>
			<ymin>478</ymin>
			<xmax>1188</xmax>
			<ymax>882</ymax>
		</bndbox>
	</object>
	<object>
		<name>quadruple</name>
		<pose>Unspecified</pose>
		<truncated>0</truncated>
		<difficult>0</difficult>
		<bndbox>
			<xmin>1201</xmin>
			<ymin>478</ymin>
			<xmax>1786</xmax>
			<ymax>882</ymax>
		</bndbox>
	</object>
	<object>
		<name>quadruple</name>
		<pose>Unspecified</pose>
		<truncated>0</truncated>
		<difficult>0</difficult>
		<bndbox>
			<xmin>1792</xmin>
			<ymin>486</ymin>
			<xmax>2377</xmax>
			<ymax>890</ymax>
		</bndbox>
	</object>
	<object>
		<name>row</name>
		<pose>Unspecified</pose>
		<truncated>1</truncated>
		<difficult>0</difficult>
		<bndbox>
			<xmin>24</xmin>
			<ymin>1</ymin>
			<xmax>2400</xmax>
			<ymax>134</ymax>
		</bndbox>
	</object>
	<object>
		<name>row</name>
		<pose>Unspecified</pose>
		<truncated>0</truncated>
		<difficult>0</difficult>
		<bndbox>
			<xmin>17</xmin>
			<ymin>134</ymin>
			<xmax>2383</xmax>
			<ymax>477</ymax>
		</bndbox>
	</object>
	<object>
		<name>row</name>
		<pose>Unspecified</pose>
		<truncated>1</truncated>
		<difficult>0</difficult>
		<bndbox>
			<xmin>12</xmin>
			<ymin>488</ymin>
			<xmax>2400</xmax>
			<ymax>890</ymax>
		</bndbox>
	</object>
</annotation>
