<annotation>
	<folder>Images</folder>
	<filename>0051.png</filename>
	<path>D:\20190529data_label\D1_100\Images\0051.png</path>
	<source>
		<database>Unknown</database>
	</source>
	<size>
		<width>2400</width>
		<height>1380</height>
		<depth>3</depth>
	</size>
	<segmented>0</segmented>
	<object>
		<name>btn-active</name>
		<pose>Unspecified</pose>
		<truncated>0</truncated>
		<difficult>0</difficult>
		<bndbox>
			<xmin>30</xmin>
			<ymin>2</ymin>
			<xmax>230</xmax>
			<ymax>112</ymax>
		</bndbox>
	</object>
	<object>
		<name>btn-active</name>
		<pose>Unspecified</pose>
		<truncated>1</truncated>
		<difficult>0</difficult>
		<bndbox>
			<xmin>232</xmin>
			<ymin>1</ymin>
			<xmax>432</xmax>
			<ymax>110</ymax>
		</bndbox>
	</object>
	<object>
		<name>btn-active</name>
		<pose>Unspecified</pose>
		<truncated>0</truncated>
		<difficult>0</difficult>
		<bndbox>
			<xmin>59</xmin>
			<ymin>326</ymin>
			<xmax>259</xmax>
			<ymax>436</ymax>
		</bndbox>
	</object>
	<object>
		<name>small-title</name>
		<pose>Unspecified</pose>
		<truncated>0</truncated>
		<difficult>0</difficult>
		<bndbox>
			<xmin>63</xmin>
			<ymin>199</ymin>
			<xmax>224</xmax>
			<ymax>273</ymax>
		</bndbox>
	</object>
	<object>
		<name>text</name>
		<pose>Unspecified</pose>
		<truncated>0</truncated>
		<difficult>0</difficult>
		<bndbox>
			<xmin>66</xmin>
			<ymin>273</ymin>
			<xmax>788</xmax>
			<ymax>329</ymax>
		</bndbox>
	</object>
	<object>
		<name>single</name>
		<pose>Unspecified</pose>
		<truncated>0</truncated>
		<difficult>0</difficult>
		<bndbox>
			<xmin>14</xmin>
			<ymin>133</ymin>
			<xmax>2390</xmax>
			<ymax>486</ymax>
		</bndbox>
	</object>
	<object>
		<name>row</name>
		<pose>Unspecified</pose>
		<truncated>1</truncated>
		<difficult>0</difficult>
		<bndbox>
			<xmin>1</xmin>
			<ymin>1</ymin>
			<xmax>2390</xmax>
			<ymax>119</ymax>
		</bndbox>
	</object>
	<object>
		<name>row</name>
		<pose>Unspecified</pose>
		<truncated>1</truncated>
		<difficult>0</difficult>
		<bndbox>
			<xmin>1</xmin>
			<ymin>134</ymin>
			<xmax>2390</xmax>
			<ymax>470</ymax>
		</bndbox>
	</object>
</annotation>
